pymakerlab/Cloud.py
pymakerlab/__init__.py
PyMakerLab-0.1b1.dist-info/LICENSE
PyMakerLab-0.1b1.dist-info/METADATA
PyMakerLab-0.1b1.dist-info/WHEEL
PyMakerLab-0.1b1.dist-info/top_level.txt
PyMakerLab-0.1b1.dist-info/RECORD
