Metadata-Version: 2.1
Name: PyMakerLab
Version: 0.1b1
Summary: Python project managament, GUI Inteface, Cloud Functions and more!
Home-page: https://alexbronikitin.github.io/pymaker/
Author: AlexBroNikitin
Author-email: alexnikitin071209@gmail.com
License: UNKNOWN
Platform: UNKNOWN
Requires-Python: >=3.6
Requires-Dist: pyrebase
